{
    "model": 1,
    "typ": "dev",
    "api":[
        {
            "server": "http://192.168.1.4:9090/",
            "host": "http://192.168.1.4"
        },
        {
            "server": "http://localhost/",
            "host": "http://localhost"
        },
        {
            "server": "http://49.232.218.190/",
            "host": "http://49.232.218.190"
        },
        {
            "server": "http://121.89.213.223/",
            "host": "http://121.89.213.223"
        },
        {
            "server": "https://manyin.tech/",
            "host": "https://manyin.tech"
        }
    ]
}